dockergen/__init__.py
dockergen/api.py
dockergen/main.py
dockergen-0.0.2.dist-info/METADATA
dockergen-0.0.2.dist-info/WHEEL
dockergen-0.0.2.dist-info/top_level.txt
dockergen-0.0.2.dist-info/RECORD
