Metadata-Version: 2.1
Name: dockergen
Version: 0.0.2
Summary: Dockerfile generator
Home-page: https://github.com/nurpax/dockergen
Author: Janne Hellsten
Author-email: jjhellst@gmail.com
Classifier: Programming Language :: Python :: 3
Classifier: License :: OSI Approved :: MIT License
Classifier: Operating System :: OS Independent
Requires-Python: >=3.7
